pyik/__init__.py
pyik/corsika.py
pyik/ellipse.py
pyik/fit.py
pyik/locked_shelve.py
pyik/misc.py
pyik/mplext.py
pyik/numpyext.py
pyik/performance.py
pyik/rootext.py
pyik/time_conversion.py
pyik-0.10.0.dist-info/LICENSE.BSD
pyik-0.10.0.dist-info/METADATA
pyik-0.10.0.dist-info/WHEEL
pyik-0.10.0.dist-info/top_level.txt
pyik-0.10.0.dist-info/RECORD
