Metadata-Version: 2.1
Name: pyik
Version: 0.10.0
Summary: PyIK - The Python Instrument Kit
Home-page: https://github.com/hdembinski/pyik
Author: Hans Dembinski
Author-email: hans.dembinski@gmail.com
License: BSD
Platform: UNKNOWN
Classifier: Programming Language :: Python :: 2
Classifier: Programming Language :: Python :: 3
Classifier: Development Status :: 4 - Beta
Classifier: Intended Audience :: Science/Research
Classifier: Topic :: Scientific/Engineering :: Physics
Classifier: License :: OSI Approved :: BSD License
Classifier: Operating System :: OS Independent
Requires-Dist: numpy
